django_i18nkit-0.0.5.dist-info/DESCRIPTION.rst
django_i18nkit-0.0.5.dist-info/METADATA
django_i18nkit-0.0.5.dist-info/RECORD
django_i18nkit-0.0.5.dist-info/WHEEL
django_i18nkit-0.0.5.dist-info/entry_points.txt
django_i18nkit-0.0.5.dist-info/metadata.json
django_i18nkit-0.0.5.dist-info/top_level.txt
i18nkit/__init__.py
i18nkit/apps.py
i18nkit/django_extract.py
i18nkit/excel.py
i18nkit/jinja2_extract.py
i18nkit/poison.py
i18nkit/utils.py
i18nkit/management/__init__.py
i18nkit/management/commands/__init__.py
i18nkit/management/commands/ik_compile.py
i18nkit/management/commands/ik_export.py
i18nkit/management/commands/ik_extract.py
i18nkit/management/commands/ik_import.py
