Metadata-Version: 2.0
Name: django-i18nkit
Version: 0.0.5
Summary: Internationalization utilities for Django.
Home-page: UNKNOWN
Author: Aarni Koskela
Author-email: akx@iki.fi
License: MIT
Platform: UNKNOWN
Classifier: Framework :: Django
Classifier: Intended Audience :: Developers
Classifier: Operating System :: OS Independent
Classifier: Programming Language :: Python
Requires-Dist: Django (>=1.8)
Requires-Dist: babel (<3.0)
